pyrightarte/__init__.py
pyrightarte/__main__.py
pyrightarte/test.py
pyrightarte/util.py
pyrightarte-1.0.6.dist-info/METADATA
pyrightarte-1.0.6.dist-info/WHEEL
pyrightarte-1.0.6.dist-info/RECORD
