Metadata-Version: 2.1
Name: pyrightarte
Version: 1.0.6
Summary: A multitool python object notation package
Project-URL: Homepage, https://github.com/arteglaive-protein/pyright
Project-URL: Issues, https://github.com/arteglaive-protein/pyright/issues
Author-email: zewenn <zc.fallens@gmail.com>
Classifier: License :: OSI Approved :: MIT License
Classifier: Operating System :: OS Independent
Classifier: Programming Language :: Python :: 3
Requires-Python: >=3.7
